README.md
setup.py
ddns_dynu.egg-info/PKG-INFO
ddns_dynu.egg-info/SOURCES.txt
ddns_dynu.egg-info/dependency_links.txt
ddns_dynu.egg-info/entry_points.txt
ddns_dynu.egg-info/requires.txt
ddns_dynu.egg-info/top_level.txt
ddnsdynu/__init__.py
ddnsdynu/ddns.py
ddnsdynu/ipaddr.py
ddnsdynu/log.py