Metadata-Version: 2.1
Name: ddns-dynu
Version: 0.2.1
Summary: ddns for dynu.com
Home-page: https://github.com/agfn/ddns
Author: agfn
Author-email: lavender.tree9988@gmail.com
License: UNKNOWN
Project-URL: Bug Tracker, https://github.com/agfn/ddns/issues
Platform: UNKNOWN
Classifier: Programming Language :: Python :: 3
Classifier: License :: OSI Approved :: MIT License
Classifier: Operating System :: OS Independent
Requires-Python: >=3.6
